odoo/addons/account_invoice_merge/README.rst
odoo/addons/account_invoice_merge/__init__.py
odoo/addons/account_invoice_merge/__manifest__.py
odoo/addons/account_invoice_merge/i18n/account_invoice_merge.pot
odoo/addons/account_invoice_merge/i18n/am.po
odoo/addons/account_invoice_merge/i18n/ar.po
odoo/addons/account_invoice_merge/i18n/bg.po
odoo/addons/account_invoice_merge/i18n/bs.po
odoo/addons/account_invoice_merge/i18n/ca.po
odoo/addons/account_invoice_merge/i18n/ca_ES.po
odoo/addons/account_invoice_merge/i18n/cs.po
odoo/addons/account_invoice_merge/i18n/da.po
odoo/addons/account_invoice_merge/i18n/de.po
odoo/addons/account_invoice_merge/i18n/el_GR.po
odoo/addons/account_invoice_merge/i18n/en_AU.po
odoo/addons/account_invoice_merge/i18n/en_GB.po
odoo/addons/account_invoice_merge/i18n/es.po
odoo/addons/account_invoice_merge/i18n/es_AR.po
odoo/addons/account_invoice_merge/i18n/es_CL.po
odoo/addons/account_invoice_merge/i18n/es_CO.po
odoo/addons/account_invoice_merge/i18n/es_CR.po
odoo/addons/account_invoice_merge/i18n/es_DO.po
odoo/addons/account_invoice_merge/i18n/es_EC.po
odoo/addons/account_invoice_merge/i18n/es_ES.po
odoo/addons/account_invoice_merge/i18n/es_MX.po
odoo/addons/account_invoice_merge/i18n/es_PE.po
odoo/addons/account_invoice_merge/i18n/es_PY.po
odoo/addons/account_invoice_merge/i18n/es_VE.po
odoo/addons/account_invoice_merge/i18n/et.po
odoo/addons/account_invoice_merge/i18n/eu.po
odoo/addons/account_invoice_merge/i18n/fa.po
odoo/addons/account_invoice_merge/i18n/fi.po
odoo/addons/account_invoice_merge/i18n/fr.po
odoo/addons/account_invoice_merge/i18n/fr_CA.po
odoo/addons/account_invoice_merge/i18n/fr_CH.po
odoo/addons/account_invoice_merge/i18n/fr_FR.po
odoo/addons/account_invoice_merge/i18n/gl.po
odoo/addons/account_invoice_merge/i18n/gl_ES.po
odoo/addons/account_invoice_merge/i18n/he.po
odoo/addons/account_invoice_merge/i18n/hi.po
odoo/addons/account_invoice_merge/i18n/hr.po
odoo/addons/account_invoice_merge/i18n/hr_HR.po
odoo_addon_account_invoice_merge-16.0.1.0.1.10.dist-info/METADATA
odoo_addon_account_invoice_merge-16.0.1.0.1.10.dist-info/WHEEL
odoo_addon_account_invoice_merge-16.0.1.0.1.10.dist-info/top_level.txt
odoo_addon_account_invoice_merge-16.0.1.0.1.10.dist-info/RECORD
